water_drop_detection/__init__.py
water_drop_detection/main.py
water_drop_detection/NN/BatchManager.py
water_drop_detection/NN/SaveBatch.py
water_drop_detection/NN/SaveLoadModel.py
water_drop_detection/NN/TestNetwork.py
water_drop_detection/NN/__init__.py
water_drop_detection/NN/main.py
water_drop_detection/NN/data/__init__.py
water_drop_detection/NN/model/__init__.py
water_drop_detection/NN/test/__init__.py
water_drop_detection/ui/GUI.py
water_drop_detection/ui/__init__.py
water_drop_detection/ui/logo/__init__.py
water_drop_detection/ui/ui/__init__.py
water_drop_detection-0.9.dist-info/METADATA
water_drop_detection-0.9.dist-info/WHEEL
water_drop_detection-0.9.dist-info/top_level.txt
water_drop_detection-0.9.dist-info/RECORD
