Metadata-Version: 2.1
Name: water-drop-detection
Version: 0.9
Summary: A neural network that detects water drops on the surface from an image.
Home-page: UNKNOWN
Author: Aleksandr Leisle, Sofia Volodina, Alina Shitenko
Author-email: a.leisle@g.nsu.ru, s.volodina@g.nsu.ru, a.shitenko@g.nsu.ru
License: UNKNOWN
Project-URL: Documentation, https://github.com/HerrPhoton/Water_drop_detection/blob/master/Documentation.pdf
Project-URL: Bug Tracker, https://github.com/HerrPhoton/Water_drop_detection/issues
Project-URL: Homepage, https://github.com/HerrPhoton/Water_drop_detection
Platform: UNKNOWN
Classifier: Programming Language :: Python :: 3.9
Classifier: Operating System :: OS Independent
Requires-Python: ==3.9.*
Requires-Dist: opencv-python (==4.7.0.72)
Requires-Dist: segmentation-models (==1.0.1)
Requires-Dist: keras (==2.12.0)
Requires-Dist: Keras-Applications (==1.0.8)
Requires-Dist: tensorflow (==2.12.0)
Requires-Dist: matplotlib (==3.7.1)
Requires-Dist: PyQt5 (==5.15.9)
Requires-Dist: numpy (==1.23.5)
Requires-Dist: pandas (==2.0.2)
Requires-Dist: tqdm (==4.65.0)
